{
    "data": [
        {
            "id": "concepts",
            "label": "Concepts",
            "elements": [
                {
                    "id": "tableDimension",
                    "label": "Dimension",
                    "type": "DIMENSION",
                    "options": {
                        "min": 1,
                        "max": 2
                    }
                },
                {
                    "id": "tableMetric",
                    "label": "Metric",
                    "type": "METRIC",
                    "options": {
                        "min": 1,
                        "max": 1
                    }
                }
            ]
        }
    ],
    "style" : [{
        "id": "nodos",
        "label": "Nodos",
        "elements": [
            {
                "id": "nodocant",
                "label": "Cantidad de nodos",
                "type": "INTERVAL",
                "defaultValue": 10,
                "options": [{
                    "min":1
                }]
            },{
                "id": "offsetx",
                "label": "Offset X",
                "type": "INTERVAL",
                "defaultValue": 50,
                "options": [{
                    "min":0
                }]
            },{
                "id": "offsety",
                "label": "Offset Y",
                "type": "INTERVAL",
                "defaultValue": 50,
                "options": [{
                    "min":0
                }]
            }

        ] 
    }
    ],
    "interactions": [{
        "id": "filter",
        "supportedActions": ["FILTER"]
    }]
}
